<?xml version="1.0" encoding="utf-8"?>
<!DOCTYPE documentInfo>
<documentInfo url="/home/fighting/study/浙大/培养方案/培养方案_自动化（电气）.pdf">
 <pageList/>
 <generalInfo>
  <history>
   <oldPage viewport="0;C2:0.499628:0.998418:1"/>
   <oldPage viewport="1;C2:0.499628:0.973101:1"/>
   <oldPage viewport="2;C2:0.499628:0.0379747:1"/>
   <oldPage viewport="1;C2:0.499628:0.05327:1"/>
   <oldPage viewport="0;C2:0.499628:0.984705:1"/>
   <current viewport="1;C2:0.499628:0.23154:1"/>
  </history>
  <views>
   <view name="PageView">
    <zoom mode="1" value="1.44679"/>
   </view>
  </views>
 </generalInfo>
</documentInfo>
